compliance_checks/__init__.py
compliance_checks/carrier_line_rule.py
compliance_checks/claim_number.py
compliance_checks/ems.py
compliance_checks/required_file.py
helpers/__init__.py
helpers/alert.py
helpers/compare.py
helpers/estimate_systems.py
helpers/line_rule_term.py
helpers/messages.py
tests/__init__.py
tests/data.py
tests/test_claim_number.py
tests/test_ems.py
tests/test_line_rule.py
tests/test_required_file.py
ems_compliance_checks_pkg_MarkoDS-0.0.1.dist-info/LICENSE
ems_compliance_checks_pkg_MarkoDS-0.0.1.dist-info/METADATA
ems_compliance_checks_pkg_MarkoDS-0.0.1.dist-info/WHEEL
ems_compliance_checks_pkg_MarkoDS-0.0.1.dist-info/top_level.txt
ems_compliance_checks_pkg_MarkoDS-0.0.1.dist-info/RECORD
